feets/__init__.py
feets/core.py
feets/features.py
feets/io.py
feets/preprocess.py
feets/runner.py
feets/datasets/__init__.py
feets/datasets/base.py
feets/datasets/macho.py
feets/datasets/ogle3.py
feets/datasets/synthetic.py
feets/datasets/data/ogle3.txt.bz2
feets/datasets/data/macho/lc_1.3444.614.tar.bz2
feets/datasets/data/macho/lc_1.3567.1310.tar.bz2
feets/datasets/data/macho/lc_1.3568.288.tar.bz2
feets/datasets/data/macho/lc_1.4176.155.tar.bz2
feets/datasets/data/macho/lc_1.4418.1930.tar.bz2
feets/datasets/data/macho/lc_1.4652.1527.tar.bz2
feets/datasets/data/macho/lc_10.4279.1493.tar.bz2
feets/datasets/data/macho/lc_111.23746.772.tar.bz2
feets/datasets/data/macho/lc_2.4907.2086.tar.bz2
feets/datasets/data/macho/lc_58.6272.729.tar.bz2
feets/extractors/__init__.py
feets/extractors/ext_amplitude.py
feets/extractors/ext_anderson_darling.py
feets/extractors/ext_astropy_lomb_scargle.py
feets/extractors/ext_autocor_length.py
feets/extractors/ext_bazin_fit.py
feets/extractors/ext_beyond_n_std.py
feets/extractors/ext_car.py
feets/extractors/ext_color.py
feets/extractors/ext_con.py
feets/extractors/ext_cusum.py
feets/extractors/ext_dmdt.py
feets/extractors/ext_duration.py
feets/extractors/ext_eta.py
feets/extractors/ext_eta_color.py
feets/extractors/ext_eta_e.py
feets/extractors/ext_excess_variance.py
feets/extractors/ext_fourier_components.py
feets/extractors/ext_gskew.py
feets/extractors/ext_inter_percentile_range.py
feets/extractors/ext_light_curve_lomb_scargle.py
feets/extractors/ext_linear_fit.py
feets/extractors/ext_linear_trend.py
feets/extractors/ext_linexp_fit.py
feets/extractors/ext_max_slope.py
feets/extractors/ext_max_time_interval.py
feets/extractors/ext_mean.py
feets/extractors/ext_mean_variance.py
feets/extractors/ext_median.py
feets/extractors/ext_median_abs_dev.py
feets/extractors/ext_median_amplitude.py
feets/extractors/ext_median_brp.py
feets/extractors/ext_min_time_interval.py
feets/extractors/ext_otsu_split.py
feets/extractors/ext_pair_slope_trend.py
feets-1.0.1.dist-info/licenses/LICENSE
feets-1.0.1.dist-info/METADATA
feets-1.0.1.dist-info/WHEEL
feets-1.0.1.dist-info/top_level.txt
feets-1.0.1.dist-info/RECORD
